Metadata-Version: 2.1
Name: proyectojhanel
Version: 0.1
Summary: Trabajo de modulos
Author: jhanelsollesgarcia
Author-email: jhanelsollesgarcia2@gmail.com
License: MIT
